{
  "decisionObjects": [
    {
      "name": "NETHERITE_INGOT",
      "weight": 0.4,
      "value": 2000,
      "min": 1,
      "max": 8,
      "step": 1
    },
    {
      "name": "ANCIENT_DEBRIS",
      "weight": 0.4,
      "value": 500,
      "min": 1,
      "max": 8,
      "step": 1
    },
    {
      "name": "DIAMOND",
      "weight": 2.0,
      "value": 300,
      "min": 1,
      "max": 64,
      "step": 1
    },
    {
      "name": "EMERALD",
      "weight": 0.6,
      "value": 300,
      "min": 1,
      "max": 64,
      "step": 1
    },
    {
      "name": "GOLD_INGOT",
      "weight": 0.8,
      "value": 32,
      "min": 4,
      "max": 64,
      "step": 4
    },
    {
      "name": "IRON_INGOT",
      "weight": 1.5,
      "value": 16,
      "min": 4,
      "max": 128,
      "step": 4
    },
    {
      "name": "COAL",
      "weight": 1.0,
      "value": 8,
      "min": 8,
      "max": 128,
      "step": 8
    },
    {
      "name": "QUARTZ",
      "weight": 0.3,
      "value": 32,
      "min": 8,
      "max": 64,
      "step": 8
    },
    {
      "name": "FLINT",
      "weight": 0.5,
      "value": 24,
      "min": 8,
      "max": 64,
      "step": 8
    }
  ]
}